compiler_opt/__init__.py
compiler_opt/package_config.py
compiler_opt/type_map.py
compiler_opt/benchmark/__init__.py
compiler_opt/benchmark/benchmark_chromium.py
compiler_opt/benchmark/benchmark_llvm_test_suite.py
compiler_opt/benchmark/benchmark_report.py
compiler_opt/benchmark/benchmark_report_converter.py
compiler_opt/benchmark/benchmark_report_test.py
compiler_opt/benchmark/benchmarking_utils.py
compiler_opt/benchmark/filter_tests.py
compiler_opt/benchmark/gtest_executable_utils.py
compiler_opt/benchmark/list_gtests.py
compiler_opt/distributed/__init__.py
compiler_opt/distributed/buffered_scheduler.py
compiler_opt/distributed/buffered_scheduler_test.py
compiler_opt/distributed/worker.py
compiler_opt/distributed/worker_test.py
compiler_opt/distributed/local/__init__.py
compiler_opt/distributed/local/local_worker_manager.py
compiler_opt/distributed/local/local_worker_manager_test.py
compiler_opt/es/__init__.py
compiler_opt/es/blackbox_learner.py
compiler_opt/es/blackbox_learner_test.py
compiler_opt/es/blackbox_optimizers.py
compiler_opt/es/blackbox_optimizers_test.py
compiler_opt/es/es_trainer.py
compiler_opt/es/es_trainer_lib.py
compiler_opt/es/es_worker.py
compiler_opt/es/gradient_ascent_optimization_algorithms.py
compiler_opt/es/gradient_ascent_optimization_algorithms_test.py
compiler_opt/es/policy_utils.py
compiler_opt/es/policy_utils_test.py
compiler_opt/rl/__init__.py
compiler_opt/rl/agent_config.py
compiler_opt/rl/agent_config_test.py
compiler_opt/rl/best_trajectory.py
compiler_opt/rl/best_trajectory_test.py
compiler_opt/rl/compilation_runner.py
compiler_opt/rl/compilation_runner_test.py
compiler_opt/rl/constant.py
compiler_opt/rl/constant_value_network.py
compiler_opt/rl/constant_value_network_test.py
compiler_opt/rl/corpus.py
compiler_opt/rl/corpus_test.py
compiler_opt/rl/data_collector.py
compiler_opt/rl/data_collector_test.py
compiler_opt/rl/data_reader.py
compiler_opt/rl/data_reader_test.py
compiler_opt/rl/env.py
compiler_opt/rl/env_test.py
ml_compiler_opt-0.0.1.dev202401270006.dist-info/LICENSE
ml_compiler_opt-0.0.1.dev202401270006.dist-info/METADATA
ml_compiler_opt-0.0.1.dev202401270006.dist-info/WHEEL
ml_compiler_opt-0.0.1.dev202401270006.dist-info/top_level.txt
ml_compiler_opt-0.0.1.dev202401270006.dist-info/RECORD
