Metadata-Version: 2.1
Name: ml-compiler-opt
Version: 0.0.1.dev202401270006
Summary: Tooling for ML in LLVM
Requires-Python: <3.11,>=3.8
License-File: LICENSE
Requires-Dist: absl-py >=1.0.0
Requires-Dist: gin-config >=0.5.0
Requires-Dist: psutil >=5.9.0
Requires-Dist: tf-agents >=0.16.0
Requires-Dist: tensorflow >=2.12.0
Requires-Dist: dm-reverb >=0.11.0
